nola_tools/__init__.py
nola_tools/_version.py
nola_tools/build.py
nola_tools/nalja.py
nola_tools/nolja.py
nola_tools/repo.py
nola_tools/utils/__init__.py
nola_tools/utils/config_file.py
nola_tools/utils/version_check.py
nola_tools-0.9.2.dist-info/licenses/LICENSE
nola_tools-0.9.2.dist-info/METADATA
nola_tools-0.9.2.dist-info/WHEEL
nola_tools-0.9.2.dist-info/entry_points.txt
nola_tools-0.9.2.dist-info/pbr.json
nola_tools-0.9.2.dist-info/top_level.txt
nola_tools-0.9.2.dist-info/RECORD
