Metadata-Version: 2.4
Name: nola-tools
Version: 0.9.2
Summary: Nol.A-SDK Command Line Interface
Author-email: "COX Co., Ltd." <dev@coxlab.kr>
License-Expression: MIT
Project-URL: Homepage, https://github.com/CoXlabInc/Nol.A-Tools
Classifier: Programming Language :: Python :: 3
Classifier: Operating System :: OS Independent
Requires-Python: >=3.8
License-File: LICENSE
Requires-Dist: GitPython
Requires-Dist: argparse
Dynamic: license-file
